hunyuan_paper/__init__.py
hunyuan_paper/__main__.py
hunyuan_paper/exceptions.py
hunyuan_paper/main.py
hunyuan_paper-0.1.3.dist-info/METADATA
hunyuan_paper-0.1.3.dist-info/WHEEL
hunyuan_paper-0.1.3.dist-info/entry_points.txt
hunyuan_paper-0.1.3.dist-info/top_level.txt
hunyuan_paper-0.1.3.dist-info/RECORD
