Metadata-Version: 2.4
Name: hunyuan-paper
Version: 0.1.3
Summary: Hunyuan Paper
Author: YuanqiMcp
Author-email: YuanqiMcp <yuanqi_mcp@tencent.com>
Keywords: hunyuan,paper,mcp
Classifier: Development Status :: 4 - Beta
Classifier: Intended Audience :: Developers
Classifier: License :: OSI Approved :: MIT License
Classifier: Programming Language :: Python :: 3
Classifier: Programming Language :: Python :: 3.11
Classifier: Programming Language :: Python :: 3.12
Requires-Python: >=3.10
Requires-Dist: mcp[cli]>=1.6.0
Requires-Dist: httpx==0.28.1
Requires-Dist: uvicorn==0.34.2
Dynamic: author
Dynamic: requires-python
